sousflow/__init__.py
sousflow-0.1.0.dist-info/LICENSE
sousflow-0.1.0.dist-info/METADATA
sousflow-0.1.0.dist-info/WHEEL
sousflow-0.1.0.dist-info/RECORD
